raspstat
build
