Metadata-Version: 1.1
Name: Raspstat
Version: 0.1.1
Summary: Python wrapper to get system stats in linux
Home-page: https://github.com/JWebCoder/raspstat
Author: JWebCoder
Author-email: joao87moura@gmail.com
License: GNU GPLv2
Keywords: raspberry stats linux
Platform: UNKNOWN
Classifier: Development Status :: 5 - Production/Stable
Classifier: Intended Audience :: Developers
Classifier: License :: OSI Approved :: GNU General Public License v3 or later (GPLv3+)
Classifier: Programming Language :: Python :: 2
Classifier: Programming Language :: Python :: 2.6
Classifier: Programming Language :: Python :: 2.7
Classifier: Programming Language :: Python :: 3
Classifier: Programming Language :: Python :: 3.2
Classifier: Programming Language :: Python :: 3.3
Classifier: Programming Language :: Python :: 3.4
Classifier: Topic :: Internet :: WWW/HTTP :: Indexing/Search
